setup.py
sci_stats_dist/Binomialdistribution.py
sci_stats_dist/Gaussiandistribution.py
sci_stats_dist/Generaldistribution.py
sci_stats_dist/__init__.py
sci_stats_dist.egg-info/PKG-INFO
sci_stats_dist.egg-info/SOURCES.txt
sci_stats_dist.egg-info/dependency_links.txt
sci_stats_dist.egg-info/not-zip-safe
sci_stats_dist.egg-info/top_level.txt