Metadata-Version: 1.0
Name: sci-stats-dist
Version: 0.0.1
Summary: this package includes statistical distributions like binomial and gaussain distribution
Home-page: https://github.com/mohamed-ashry7/sci-stats-dist.git
Author: Mohamed Ashry
Author-email: UNKNOWN
License: UNKNOWN
Platform: UNKNOWN
